telethon_bot/__init__.py
telethon_bot/bot.py
telethon_bot/conf.py
telethon_bot/handlers/__init__.py
telethon_bot/handlers/basics.py
telethon_bot/types.py
telethon_bot/utils.py
telethon_bot-0.1.0.dist-info/entry_points.txt
telethon_bot-0.1.0.dist-info/WHEEL
telethon_bot-0.1.0.dist-info/METADATA
telethon_bot-0.1.0.dist-info/RECORD
