Metadata-Version: 2.1
Name: telethon-bot
Version: 0.1.0
Summary: 
Author: aahnik
Author-email: daw@aahnik.dev
Requires-Python: >=3.9,<4.0
Classifier: Programming Language :: Python :: 3
Classifier: Programming Language :: Python :: 3.9
Requires-Dist: Pillow (>=8.2.0,<9.0.0)
Requires-Dist: Telethon (>=1.21.1,<2.0.0)
Requires-Dist: cryptg (>=0.2.post4,<0.3)
Requires-Dist: python-dotenv (>=0.17.1,<0.18.0)
Requires-Dist: rich (>=10.3.0,<11.0.0)
